{
	"info": {
		"_postman_id": "2336d242-2d75-4b32-b30a-476dc5e9b62e",
		"name": "Pokedex Collection",
		"schema": "https://schema.getpostman.com/json/collection/v2.1.0/collection.json",
		"_exporter_id": "19149552"
	},
	"item": [
		{
			"name": "Search Pokemons",
			"request": {
				"method": "GET",
				"header": [],
				"url": {
					"raw": "http://64.226.124.118:8084/pokemons",
					"protocol": "http",
					"host": [
						"64",
						"226",
						"124",
						"118"
					],
					"port": "8084",
					"path": [
						"pokemons"
					],
					"query": [
						{
							"key": "name",
							"value": "w",
							"disabled": true
						},
						{
							"key": "type",
							"value": "BUG",
							"disabled": true
						},
						{
							"key": "favorites",
							"value": "true",
							"disabled": true
						}
					]
				}
			},
			"response": []
		},
		{
			"name": "Find pokemon by Id",
			"protocolProfileBehavior": {
				"disableBodyPruning": true
			},
			"request": {
				"method": "GET",
				"header": [],
				"body": {
					"mode": "raw",
					"raw": ""
				},
				"url": {
					"raw": "http://64.226.124.118:8084/pokemons/11ffdfce-27a3-40bf-b421-03691e0cc6fd",
					"protocol": "http",
					"host": [
						"64",
						"226",
						"124",
						"118"
					],
					"port": "8084",
					"path": [
						"pokemons",
						"11ffdfce-27a3-40bf-b421-03691e0cc6fd"
					]
				}
			},
			"response": []
		},
		{
			"name": "Register Pokemons",
			"request": {
				"method": "POST",
				"header": [],
				"body": {
					"mode": "raw",
					"raw": ""
				},
				"url": {
					"raw": "http://64.226.124.118:8084/pokemons",
					"protocol": "http",
					"host": [
						"64",
						"226",
						"124",
						"118"
					],
					"port": "8084",
					"path": [
						"pokemons"
					]
				}
			},
			"response": []
		},
		{
			"name": "Mark pokemon as favorite",
			"request": {
				"method": "PATCH",
				"header": [],
				"url": {
					"raw": "http://64.226.124.118:8084/pokemons/11ffdfce-27a3-40bf-b421-03691e0cc6fd/mark",
					"protocol": "http",
					"host": [
						"64",
						"226",
						"124",
						"118"
					],
					"port": "8084",
					"path": [
						"pokemons",
						"11ffdfce-27a3-40bf-b421-03691e0cc6fd",
						"mark"
					]
				}
			},
			"response": []
		},
		{
			"name": "Mark pokemon as favorite",
			"request": {
				"method": "PATCH",
				"header": [],
				"url": {
					"raw": "http://64.226.124.118:8084/pokemons/11ffdfce-27a3-40bf-b421-03691e0cc6fd/unmark",
					"protocol": "http",
					"host": [
						"64",
						"226",
						"124",
						"118"
					],
					"port": "8084",
					"path": [
						"pokemons",
						"11ffdfce-27a3-40bf-b421-03691e0cc6fd",
						"unmark"
					]
				}
			},
			"response": []
		}
	]
}